challengeturn/__init__.py
challengeturn/main.py
challengeturn/prompts.py
challengeturn-2025.12.21183136.dist-info/METADATA
challengeturn-2025.12.21183136.dist-info/WHEEL
challengeturn-2025.12.21183136.dist-info/top_level.txt
challengeturn-2025.12.21183136.dist-info/RECORD
