Metadata-Version: 2.4
Name: challengeturn
Version: 2025.12.21183136
Summary: A new package that analyzes user input text to determine if it expresses a challenge or a statement of inability, and returns a structured, encouraging response. It uses pattern matching to identify p
Author-email: challengeturn <hi@eugene.plus>
License: MIT
Project-URL: Homepage, https://github.com/chigwell/challengeturn
Requires-Python: >=3.9
Requires-Dist: langchain-llm7>=0.0.0
Requires-Dist: llmatch-messages>=0.0.0
Requires-Dist: langchain-core>=0.3.0
